langchain_pubnub/__init__.py
langchain_pubnub/py.typed
langchain_pubnub/tools.py
langchain_pubnub-0.1.4.dist-info/METADATA
langchain_pubnub-0.1.4.dist-info/WHEEL
langchain_pubnub-0.1.4.dist-info/licenses/LICENSE
langchain_pubnub-0.1.4.dist-info/RECORD
