Metadata-Version: 2.4
Name: langchain-pubnub
Version: 0.1.4
Summary: LangChain integration for PubNub real-time messaging
Project-URL: Homepage, https://github.com/yourusername/langchain-pubnub
Project-URL: Documentation, https://github.com/yourusername/langchain-pubnub#readme
Project-URL: Repository, https://github.com/yourusername/langchain-pubnub
Project-URL: Changelog, https://github.com/yourusername/langchain-pubnub/blob/main/CHANGELOG.md
Author-email: Your Name <your.email@example.com>
License-Expression: MIT
License-File: LICENSE
Keywords: ai,langchain,llm,messaging,pubnub,pubsub,real-time,tools
Classifier: Development Status :: 4 - Beta
Classifier: Intended Audience :: Developers
Classifier: License :: OSI Approved :: MIT License
Classifier: Operating System :: OS Independent
Classifier: Programming Language :: Python :: 3
Classifier: Programming Language :: Python :: 3.9
Classifier: Programming Language :: Python :: 3.10
Classifier: Programming Language :: Python :: 3.11
Classifier: Programming Language :: Python :: 3.12
Classifier: Programming Language :: Python :: 3.13
Classifier: Programming Language :: Python :: 3.14
Classifier: Topic :: Communications :: Chat
Classifier: Topic :: Scientific/Engineering :: Artificial Intelligence
Classifier: Topic :: Software Development :: Libraries :: Python Modules
Requires-Python: >=3.9
Requires-Dist: langchain-core<1.0.0,>=0.2.0
Requires-Dist: pubnub<11.0.0,>=10.0.0
Requires-Dist: pydantic<3.0.0,>=2.0.0
Provides-Extra: dev
Requires-Dist: langchain-core<1.0.0,>=0.2.0; extra == 'dev'
